{"version":"2.1","user":{"fname":null,"lname":null},"video":{"seasons":[{"id":70223400,"title":"Series 1","year":2011,"seq":1,"episodes":[{"id":70223401,"episodeId":70223401,"synopsis":"The routine life of Gloucester woman Janet Leach is dramatically transformed when she asked by police to sit in as \"appropriate adult.\"","title":"Episode 1","seq":1,"runtime":3855,"creditsOffset":3819,"autoplayable":true,"start":1404198000000,"end":1467356400000,"hd":true,"requiresPin":false,"progressImageRoot":"http://tp.akam.nflximg.com/tpa1/524/1348590524/","stills":[{"w":1920,"h":1080,"url":"http://so1.akam.nflximg.com/soa5/665/1355018665.jpg"}],"bookmark":{"offset":-1,"watchedDate":0}},{"id":70223402,"episodeId":70223402,"synopsis":"With Janet Leach no longer involved in the police interviews, Fred West refuses to speak to the police.","title":"Episode 2","seq":2,"runtime":4144,"creditsOffset":4108,"autoplayable":true,"start":1404198000000,"end":1467356400000,"hd":true,"requiresPin":false,"progressImageRoot":"http://tp.akam.nflximg.com/tpa1/969/1349471969/","stills":[{"w":1920,"h":1080,"url":"http://so0.akam.nflximg.com/soa2/648/1358547648.jpg"}],"bookmark":{"offset":-1,"watchedDate":0}}]}],"type":"show","id":70224741,"title":"Appropriate Adult","synopsis":"This dark crime series focuses on the tension between an accused killer and the woman appointed to protect his interests during police questioning.","rating":"NR","cinematch":{"value":3.6,"type":"predicted"},"requiresPin":false,"artwork":[{"w":1280,"h":720,"url":"http://cdn0.nflximg.net/images/8382/9928382.jpg"},{"w":1280,"h":720,"url":"http://cdn0.nflximg.net/images/8382/9928382.jpg"}],"boxart":[{"w":426,"h":607,"url":"http://cdn0.nflximg.net/images/8416/9928416.jpg"},{"w":284,"h":405,"url":"http://cdn1.nflximg.net/images/8415/9928415.jpg"}]}}
