{"version":"2.1","user":{"fname":null,"lname":null},"video":{"type":"show","id":70287758,"title":"Unsere M\u00FCtter, unsere V\u00E4ter","synopsis":"Five young friends meet in Berlin in 1941, but it may be their last time together as the events of World War II tear them apart.","rating":"NR","cinematch":{"value":5.0,"type":"predicted"},"requiresPin":false,"artwork":[{"w":1280,"h":720,"url":"http://cdn1.nflximg.net/images/8671/11018671.jpg"},{"w":1280,"h":720,"url":"http://cdn1.nflximg.net/images/8671/11018671.jpg"}],"boxart":[{"w":426,"h":607,"url":"http://cdn1.nflximg.net/images/0325/9730325.jpg"},{"w":284,"h":405,"url":"http://cdn0.nflximg.net/images/0324/9730324.jpg"}],"seasons":[{"id":70286691,"title":"Generation War","year":2013,"seq":1,"episodes":[{"id":70286692,"episodeId":70286692,"synopsis":"Berlin 1941: five friends say goodbye and will try to see each other once the war is over. They have no idea how much their lives will have changed.","title":"Episode 1","seq":1,"runtime":5434,"creditsOffset":5404,"autoplayable":true,"start":1404543600000,"end":1467702000000,"hd":true,"requiresPin":false,"progressImageRoot":"http://tp.akam.nflximg.com/tpa2/647/1551890647/","stills":[{"w":1920,"h":1080,"url":"http://so0.akam.nflximg.com/soa2/694/1554147694.jpg"}],"bookmark":{"offset":-1,"watchedDate":0}},{"id":70286693,"episodeId":70286693,"synopsis":"Two years later, Wilhelm, Friedhelm, and Charlotte are at the Eastern Front. Greta is a singer and her Jewish friend Viktor fears for his life.","title":"Episode 2","seq":2,"runtime":5311,"creditsOffset":5300,"autoplayable":true,"start":1404543600000,"end":1467702000000,"hd":true,"requiresPin":false,"progressImageRoot":"http://tp.akam.nflximg.com/tpa3/151/1551739151/","stills":[{"w":1920,"h":1080,"url":"http://so1.akam.nflximg.com/soa4/183/1553658183.jpg"}],"bookmark":{"offset":-1,"watchedDate":0}},{"id":70286694,"episodeId":70286694,"synopsis":"Greta has been arrested, Charlotte has been seized by the Russians, and Friedhelm and Viktor are facing each other. The war's over but is it really?","title":"Episode 3","seq":3,"runtime":5674,"creditsOffset":5644,"autoplayable":true,"start":1404543600000,"end":1467702000000,"hd":true,"requiresPin":false,"progressImageRoot":"http://tp.akam.nflximg.com/tpa1/903/1557347903/","stills":[{"w":1920,"h":1080,"url":"http://so0.akam.nflximg.com/soa4/416/1559645416.jpg"}],"bookmark":{"offset":-1,"watchedDate":0}}]}]}}
