{"version":"2.1","user":{"fname":null,"lname":null},"video":{"seasons":[{"id":80032056,"title":"Season 1","year":2014,"seq":1,"episodes":[{"id":80029602,"episodeId":80029602,"synopsis":"Accounts from inmates, officers and the warden of a maximum-security prison shed light on the disturbing realities of living in solitary confinement.","title":"Frontline: Locked Up in America: Solitary Nation","seq":1,"runtime":3188,"creditsOffset":3130,"autoplayable":true,"start":1420099200000,"end":1451635200000,"hd":true,"requiresPin":false,"progressImageRoot":"http://tp.akam.nflximg.com/tpa4/836/1166665836/","stills":[{"w":1916,"h":1080,"url":"http://so0.akam.nflximg.com/soa1/322/1185907322.jpg"}],"bookmark":{"offset":-1,"watchedDate":0}},{"id":80029603,"episodeId":80029603,"synopsis":"Focusing on four housing project residents and their struggles with the law, \"Frontline\" examines the impact of mass incarceration in America.","title":"Frontline: Locked Up in America: Prison State","seq":2,"runtime":4994,"creditsOffset":4940,"autoplayable":true,"start":1420099200000,"end":1451635200000,"hd":true,"requiresPin":false,"progressImageRoot":"http://tp.akam.nflximg.com/tpa2/422/987172422/","stills":[{"w":1916,"h":1080,"url":"http://so1.akam.nflximg.com/soa2/822/1038931822.jpg"}],"bookmark":{"offset":-1,"watchedDate":0}}]}],"type":"show","id":80032055,"title":"Locked Up in America","synopsis":"\"Frontline\" goes inside America's prison system, exploring controversies around solitary confinement and attempts to break the cycle of incarceration.","rating":"TV-MA","cinematch":{"value":3.6,"type":"predicted"},"requiresPin":false,"artwork":[{"w":1280,"h":720,"url":"http://cdn0.nflximg.net/images/6522/11956522.jpg"},{"w":1280,"h":720,"url":"http://cdn0.nflximg.net/images/6522/11956522.jpg"}],"boxart":[{"w":426,"h":607,"url":"http://cdn0.nflximg.net/images/6540/11956540.jpg"},{"w":284,"h":405,"url":"http://cdn0.nflximg.net/images/6538/11956538.jpg"}]}}
